Workbook

Sheet Process_Data
A1: BUSINESS PROCESS OPTIMIZATION — Raw Data
A2: Process_ID | B2: Process | C2: Step | D2: Department | E2: Start_Time | F2: End_Time | G2: Duration_Mins | H2: Cost_INR | I2: Status | J2: Owner | K2: Process_Type | L2: Priority
A3: PRC001 | B3: Inventory Check | C3: Initiation | D3: Sales | E3: 2024-01-30 10:47 | F3: 2024-01-30 11:59 | G3: 72 | H3: 1986.18 | I3: Delayed | J3: Rohit Mehta | K3: Strategic | L3: High
A4: PRC002 | B4: Order Fulfillment | C4: Verification | D4: HR | E4: 2024-03-06 08:35 | F4: 2024-03-06 09:44 | G4: 69 | H4: 3383.15 | I4: Delayed | J4: Meena Iyer | K4: Support | L4: Medium
A5: PRC003 | B5: Procurement | C5: Completion | D5: Operations | E5: 2024-03-31 14:21 | F5: 2024-03-31 15:11 | G5: 50 | H5: 4529.13 | I5: Completed | J5: Karan Singh | K5: Core | L5: High
A6: PRC004 | B6: Quality Check | C6: Verification | D6: Procurement | E6: 2024-03-19 12:02 | F6: 2024-03-19 13:40 | G6: 98 | H6: 11081.11 | I6: Delayed | J6: Rohit Mehta | K6: Strategic | L6: High
A7: PRC005 | B7: IT Support | C7: Completion | D7: Procurement | E7: 2024-01-26 09:02 | F7: 2024-01-26 11:39 | G7: 157 | H7: 10088.32 | I7: Completed | J7: Rohit Mehta | K7: Support | L7: High
A8: PRC006 | B8: Quality Check | C8: Completion | D8: Customer Service | E8: 2024-02-17 10:23 | F8: 2024-02-17 13:15 | G8: 172 | H8: 5651.43 | I8: Completed | J8: Rohit Mehta | K8: Support | L8: Low
A9: PRC007 | B9: Invoice Processing | C9: Processing | D9: Customer Service | E9: 2024-02-05 16:14 | F9: 2024-02-05 18:01 | G9: 107 | H9: 10426.91 | I9: Completed | J9: Suresh Rajan | K9: Core | L9: Medium
A10: PRC008 | B10: Quality Check | C10: Completion | D10: Finance | E10: 2024-03-14 13:13 | F10: 2024-03-14 14:17 | G10: 64 | H10: 10003.86 | I10: Pending | J10: Vijay Kumar | K10: Support | L10: Medium
A11: PRC009 | B11: Customer Onboarding | C11: Approval | D11: Sales | E11: 2024-02-25 14:23 | F11: 2024-02-25 17:02 | G11: 159 | H11: 3680.15 | I11: Completed | J11: Anita Desai | K11: Strategic | L11: High
A12: PRC010 | B12: Order Fulfillment | C12: Verification | D12: IT | E12: 2024-01-22 14:38 | F12: 2024-01-22 17:28 | G12: 170 | H12: 1421.15 | I12: Pending | J12: Ramesh Patel | K12: Strategic | L12: Low
A13: PRC011 | B13: Vendor Payment | C13: Closure | D13: Operations | E13: 2024-03-29 16:48 | F13: 2024-03-29 17:27 | G13: 39 | H13: 4368.97 | I13: Completed | J13: Rohit Mehta | K13: Admin | L13: Medium
A14: PRC012 | B14: Customer Onboarding | C14: Update | D14: Operations | E14: 2024-03-06 10:32 | F14: 2024-03-06 11:49 | G14: 77 | H14: 13733.1 | I14: Completed | J14: Anita Desai | K14: Support | L14: High
... A52: PRC050 | B52: Vendor Payment | C52: Dispatch | D52: Customer Service | E52: 2024-02-20 13:42 | F52: 2024-02-20 13:59 | G52: 17 | H52: 10347.56 | I52: Pending | J52: Priya Nair | K52: Strategic | L52: High

Sheet KPI_Summary
A1: KPI SUMMARY — Process Efficiency Metrics
A2: KPI | B2: Formula | C2: Value | D2: Insight
A3: Total Processes | B3: =COUNTA(Process_Data!A3:A52) -> 50 | C3: =COUNTA(Process_Data!A3:A52) -> 50 | D3: Total logged process steps
A4: Completed Processes | B4: =COUNTIF(Process_Data!I3:I52,"Completed") -> 26 | C4: =COUNTIF(Process_Data!I3:I52,"Completed") -> 26 | D4: Steps successfully completed
A5: Pending Processes | B5: =COUNTIF(Process_Data!I3:I52,"Pending") -> 10 | C5: =COUNTIF(Process_Data!I3:I52,"Pending") -> 10 | D5: Steps awaiting action
A6: Delayed Processes | B6: =COUNTIF(Process_Data!I3:I52,"Delayed") -> 14 | C6: =COUNTIF(Process_Data!I3:I52,"Delayed") -> 14 | D6: Steps past deadline
A7: Avg Duration (Mins) | B7: =AVERAGE(Process_Data!G3:G52) -> 100.7 | C7: =AVERAGE(Process_Data!G3:G52) -> 100.7 | D7: Average task duration
A8: Max Duration (Mins) | B8: =MAX(Process_Data!G3:G52) -> 180 | C8: =MAX(Process_Data!G3:G52) -> 180 | D8: Longest running step
A9: Min Duration (Mins) | B9: =MIN(Process_Data!G3:G52) -> 17 | C9: =MIN(Process_Data!G3:G52) -> 17 | D9: Fastest completed step
A10: Total Cost (INR) | B10: =SUM(Process_Data!H3:H52) -> 361861.44 | C10: =SUM(Process_Data!H3:H52) -> 361861.44 | D10: Total operational cost
A11: Avg Cost per Process (INR) | B11: =AVERAGE(Process_Data!H3:H52) -> 7237.2288 | C11: =AVERAGE(Process_Data!H3:H52) -> 7237.2288 | D11: Mean cost per step
A12: Completion Rate % | B12: =COUNTIF(Process_Data!I3:I52,"Completed")/COUNTA(Process_Data!I3:I52) -> 0.52 | C12: =COUNTIF(Process_Data!I3:I52,"Completed")/COUNTA(Process_Data!I3:I52) -> 0.52 | D12: % tasks completed
A13: Delay Rate % | B13: =COUNTIF(Process_Data!I3:I52,"Delayed")/COUNTA(Process_Data!I3:I52) -> 0.28 | C13: =COUNTIF(Process_Data!I3:I52,"Delayed")/COUNTA(Process_Data!I3:I52) -> 0.28 | D13: % tasks delayed
A14: High Priority Count | B14: =COUNTIF(Process_Data!L3:L52,"High") -> 19 | C14: =COUNTIF(Process_Data!L3:L52,"High") -> 19 | D14: High priority process steps

Sheet Dept_Cost_Summary
A1: DEPARTMENT-WISE COST & EFFICIENCY SUMMARY
A2: Department | B2: Total Processes | C2: Total Cost (INR) | D2: Avg Duration (Mins) | E2: Completion Rate %
A3: Operations | B3: =COUNTIF(Process_Data!D3:D52,A3) -> 7 | C3: =SUMIF(Process_Data!D3:D52,A3,Process_Data!H3:H52) -> 47891.81 | D3: =AVERAGEIF(Process_Data!D3:D52,A3,Process_Data!G3:G52) -> 113.57143 | E3: =COUNTIFS(Process_Data!D3:D52,A3,Process_Data!I3:I52,"Completed")/COUNTIF(Process_Data!D3:D52,A3) -> 0.85714286
A4: Finance | B4: =COUNTIF(Process_Data!D3:D52,A4) -> 7 | C4: =SUMIF(Process_Data!D3:D52,A4,Process_Data!H3:H52) -> 51828.59 | D4: =AVERAGEIF(Process_Data!D3:D52,A4,Process_Data!G3:G52) -> 68.285714 | E4: =COUNTIFS(Process_Data!D3:D52,A4,Process_Data!I3:I52,"Completed")/COUNTIF(Process_Data!D3:D52,A4) -> 0.71428571
A5: IT | B5: =COUNTIF(Process_Data!D3:D52,A5) -> 3 | C5: =SUMIF(Process_Data!D3:D52,A5,Process_Data!H3:H52) -> 7848.81 | D5: =AVERAGEIF(Process_Data!D3:D52,A5,Process_Data!G3:G52) -> 137.66667 | E5: =COUNTIFS(Process_Data!D3:D52,A5,Process_Data!I3:I52,"Completed")/COUNTIF(Process_Data!D3:D52,A5) -> 0.66666667
A6: HR | B6: =COUNTIF(Process_Data!D3:D52,A6) -> 7 | C6: =SUMIF(Process_Data!D3:D52,A6,Process_Data!H3:H52) -> 44060.09 | D6: =AVERAGEIF(Process_Data!D3:D52,A6,Process_Data!G3:G52) -> 89.285714 | E6: =COUNTIFS(Process_Data!D3:D52,A6,Process_Data!I3:I52,"Completed")/COUNTIF(Process_Data!D3:D52,A6) -> 0.28571429
A7: Sales | B7: =COUNTIF(Process_Data!D3:D52,A7) -> 9 | C7: =SUMIF(Process_Data!D3:D52,A7,Process_Data!H3:H52) -> 68219.34 | D7: =AVERAGEIF(Process_Data!D3:D52,A7,Process_Data!G3:G52) -> 115.22222 | E7: =COUNTIFS(Process_Data!D3:D52,A7,Process_Data!I3:I52,"Completed")/COUNTIF(Process_Data!D3:D52,A7) -> 0.22222222
A8: Procurement | B8: =COUNTIF(Process_Data!D3:D52,A8) -> 6 | C8: =SUMIF(Process_Data!D3:D52,A8,Process_Data!H3:H52) -> 59410.27 | D8: =AVERAGEIF(Process_Data!D3:D52,A8,Process_Data!G3:G52) -> 95.666667 | E8: =COUNTIFS(Process_Data!D3:D52,A8,Process_Data!I3:I52,"Completed")/COUNTIF(Process_Data!D3:D52,A8) -> 0.66666667
A9: Logistics | B9: =COUNTIF(Process_Data!D3:D52,A9) -> 2 | C9: =SUMIF(Process_Data!D3:D52,A9,Process_Data!H3:H52) -> 18011.57 | D9: =AVERAGEIF(Process_Data!D3:D52,A9,Process_Data!G3:G52) -> 107 | E9: =COUNTIFS(Process_Data!D3:D52,A9,Process_Data!I3:I52,"Completed")/COUNTIF(Process_Data!D3:D52,A9) -> 0.5
A10: Customer Service | B10: =COUNTIF(Process_Data!D3:D52,A10) -> 9 | C10: =SUMIF(Process_Data!D3:D52,A10,Process_Data!H3:H52) -> 64590.96 | D10: =AVERAGEIF(Process_Data!D3:D52,A10,Process_Data!G3:G52) -> 99.888889 | E10: =COUNTIFS(Process_Data!D3:D52,A10,Process_Data!I3:I52,"Completed")/COUNTIF(Process_Data!D3:D52,A10) -> 0.44444444
A11: TOTAL | B11: =SUM(B3:B10) -> 50 | C11: =SUM(C3:C10) -> 361861.44 | D11: =AVERAGE(D3:D10) -> 103.32341 | E11: =AVERAGE(E3:E10) -> 0.54464286
